infrasim/__init__.py
infrasim/chassis.py
infrasim/cli.py
infrasim/config.py
infrasim/config_manager.py
infrasim/daemon.py
infrasim/global_status.py
infrasim/helper.py
infrasim/init.py
infrasim/ipmi.py
infrasim/log.py
infrasim/model.py
infrasim/package_install.py
infrasim/qemu.py
infrasim/repl.py
infrasim/socat.py
infrasim/sshim.py
infrasim/version.py
infrasim/workspace.py
infrasim/yaml_loader.py
infrasim/ipmiconsole/__init__.py
infrasim/ipmiconsole/command.py
infrasim/ipmiconsole/common.py
infrasim/ipmiconsole/env.py
infrasim/ipmiconsole/sdr.py
infrasim/ipmiconsole/sel.py
infrasim/ipmiconsole/sensor.py
infrasim/racadmsim/__init__.py
infrasim/racadmsim/api.py
infrasim/racadmsim/env.py
infrasim/racadmsim/model.py
infrasim_compute-3.5.1.data/data/infrasim/data/boot_logo.jpg
infrasim_compute-3.5.1.data/data/infrasim/data/dell_c6320/dell_c6320.emu
infrasim_compute-3.5.1.data/data/infrasim/data/dell_c6320/dell_c6320_smbios.bin
infrasim_compute-3.5.1.data/data/infrasim/data/dell_r630/dell_r630.emu
infrasim_compute-3.5.1.data/data/infrasim/data/dell_r630/dell_r630_smbios.bin
infrasim_compute-3.5.1.data/data/infrasim/data/dell_r730/dell_r730.emu
infrasim_compute-3.5.1.data/data/infrasim/data/dell_r730/dell_r730_smbios.bin
infrasim_compute-3.5.1.data/data/infrasim/data/dell_r730xd/dell_r730xd.emu
infrasim_compute-3.5.1.data/data/infrasim/data/dell_r730xd/dell_r730xd_smbios.bin
infrasim_compute-3.5.1.data/data/infrasim/data/drive/SEAGATE_ST600MM0088.bin
infrasim_compute-3.5.1.data/data/infrasim/data/drive/TOSHIBA_PX04SRB192.bin
infrasim_compute-3.5.1.data/data/infrasim/data/quanta_d51/quanta_d51.emu
infrasim_compute-3.5.1.data/data/infrasim/data/quanta_d51/quanta_d51_smbios.bin
infrasim_compute-3.5.1.data/data/infrasim/data/quanta_t41/quanta_t41.emu
infrasim_compute-3.5.1.data/data/infrasim/data/quanta_t41/quanta_t41_smbios.bin
infrasim_compute-3.5.1.data/data/infrasim/data/s2600kp/s2600kp.emu
infrasim_compute-3.5.1.dist-info/DESCRIPTION.rst
infrasim_compute-3.5.1.dist-info/METADATA
infrasim_compute-3.5.1.dist-info/RECORD
infrasim_compute-3.5.1.dist-info/WHEEL
infrasim_compute-3.5.1.dist-info/metadata.json
infrasim_compute-3.5.1.dist-info/pbr.json
infrasim_compute-3.5.1.dist-info/top_level.txt
