Metadata-Version: 2.0
Name: infrasim-compute
Version: 3.5.1
Summary: Bare-metal server simulator
Home-page: http://www.emc.com
Author: EMC
Author-email: infrasim.dev@emc.com
License: 'Apache 2.0'
Platform: UNKNOWN
Classifier: Development Status :: 5 - Production/Stable
Classifier: Environment :: Console
Classifier: Intended Audience :: Information Technology
Classifier: License :: OSI Approved :: Apache Software License
Classifier: Operating System :: POSIX :: Linux
Classifier: Programming Language :: Python
Classifier: Programming Language :: Python :: 2
Classifier: Programming Language :: Python :: 2.7
Requires-Dist: MarkupSafe (==0.23)
Requires-Dist: cffi (==1.7.0)
Requires-Dist: coverage (>=3.6)
Requires-Dist: ecdsa (==0.13)
Requires-Dist: enum34 (==1.1.6)
Requires-Dist: idna (==2.1)
Requires-Dist: ipaddress (==1.0.16)
Requires-Dist: jinja2 (==2.9)
Requires-Dist: nose (==1.3.7)
Requires-Dist: nose-cov (==1.6)
Requires-Dist: paramiko (==2.0.1)
Requires-Dist: pyasn1 (==0.1.9)
Requires-Dist: pycparser (==2.14)
Requires-Dist: pycrypto (==2.6.1)
Requires-Dist: pyyaml (==3.11)
Requires-Dist: requests (==2.11.1)
Requires-Dist: six (==1.10.0)
Requires-Dist: ssh (==1.8.0)
Requires-Dist: texttable (==0.8.7)
